orca_rs-0.2.3.dist-info/METADATA
orca_rs-0.2.3.dist-info/WHEEL
orca_rs-0.2.3.dist-info/license_files/LICENSE
orca_rs/orca_rs.pyi
orca_rs/outputs/casscf.py
orca_rs/outputs/tddft.pyi
orca_rs/outputs/__init__.py
orca_rs/py.typed
orca_rs/__init__.py
orca_rs/orca_rs.cp311-win_amd64.pyd
orca_rs-0.2.3.dist-info/RECORD
