Metadata-Version: 2.3
Name: orca-rs
Version: 0.2.3
Classifier: Programming Language :: Rust
Classifier: Programming Language :: Python :: Implementation :: CPython
Classifier: Programming Language :: Python :: Implementation :: PyPy
License-File: LICENSE
Summary: Parser for ORCA output files.
Author-email: Felix Scherz <felixwscherz@gmail.com>
Maintainer-email: Felix Scherz <felixwscherz@gmail.com>
Requires-Python: >=3.10
Project-URL: repository, https://github.com/felixscherz/orca-rs
Project-URL: issues, https://github.com/felixscherz/orca-rs/issues
